hack4u/__init__.py
hack4u/courses.py
hack4u/utils.py
learn4u-0.6.2.dist-info/METADATA
learn4u-0.6.2.dist-info/WHEEL
learn4u-0.6.2.dist-info/top_level.txt
learn4u-0.6.2.dist-info/RECORD
