Metadata-Version: 2.4
Name: learn4u
Version: 0.6.2
Summary: Una biblioteca ligera para consultar cursos de Hack4U desde Python.
Home-page: https://hack4u.io
Author: Álvaro Luján
License: MIT
Keywords: cursos hack4u educación hacking python biblioteca
Classifier: Development Status :: 4 - Beta
Classifier: Intended Audience :: Developers
Classifier: Topic :: Education
Classifier: License :: OSI Approved :: MIT License
Classifier: Programming Language :: Python :: 3
Classifier: Programming Language :: Python :: 3.10
Classifier: Operating System :: OS Independent
Requires-Python: >=3.7
Dynamic: author
Dynamic: classifier
Dynamic: description
Dynamic: description-content-type
Dynamic: home-page
Dynamic: keywords
Dynamic: license
Dynamic: requires-python
Dynamic: summary
